imp_prof/__init__.py
imp_prof/default_config.py
imp_prof/envs.py
imp_prof/info.py
imp_prof/loader.py
imp_prof/log.py
imp_prof/main.py
imp_prof/metric.py
imp_prof/routes.py
imp_prof/types.py
imp_prof/messaging/__init__.py
imp_prof/messaging/consumer.py
imp_prof/messaging/publisher.py
imp_prof/messaging/types.py
imp_prof-0.1.2.dist-info/LICENSE
imp_prof-0.1.2.dist-info/METADATA
imp_prof-0.1.2.dist-info/WHEEL
imp_prof-0.1.2.dist-info/top_level.txt
imp_prof-0.1.2.dist-info/RECORD
