Metadata-Version: 2.1
Name: imp-prof
Version: 0.1.2
Summary: Imp-prof serves to collect and publish prometheus metrics from pre-forked server workers.
Author-email: Tom Trval <thandeus@gmail.com>
License: BSD-3-Clause
Project-URL: Homepage, https://gitlab.kajot.cz/online-casino/backend/imp-prof
Project-URL: Bug Tracker, https://gitlab.kajot.cz/online-casino/backend/imp-prof
Keywords: prometheus,fastapi,api,rest,profiling,rabbitmq,python,pika,metrics
Classifier: License :: OSI Approved :: BSD License
Classifier: Operating System :: OS Independent
Classifier: Development Status :: 5 - Production/Stable
Classifier: Intended Audience :: Developers
Classifier: Topic :: Internet :: WWW/HTTP :: WSGI :: Server
Classifier: Framework :: FastAPI
Classifier: Programming Language :: Python :: 3
Classifier: Typing :: Typed
Requires-Python: >=3.7
License-File: LICENSE
Requires-Dist: flask-restx (>=0.1)
Requires-Dist: environs (>=9.5)
Requires-Dist: fastapi (>=0.85)
Requires-Dist: starlette (>=0.20)
Requires-Dist: uvicorn[standard] (>=0.18)
Requires-Dist: pydantic (>1.10)
Requires-Dist: aio-pika (>=8.2)
Requires-Dist: pika (>=1.3)
Requires-Dist: prometheus-client (>=0.15)
Requires-Dist: orjson (>=3.8)
Requires-Dist: email-validator (>=1.0)
